alarmraj/__init__.py
alarmraj/alarm.py
alarmraj/animation.py
alarmraj/assets/a1.mp3
alarmraj/assets/audio.mp3
myalarm/__init__.py
myalarm/alarm.py
alarmraj-0.1.2.dist-info/METADATA
alarmraj-0.1.2.dist-info/WHEEL
alarmraj-0.1.2.dist-info/entry_points.txt
alarmraj-0.1.2.dist-info/top_level.txt
alarmraj-0.1.2.dist-info/RECORD
