Metadata-Version: 2.1
Name: alarmraj
Version: 0.1.2
Summary: THE ALARM CLOCK!!
Author: Aryan Raj
Requires-Dist: wheel
Requires-Dist: setuptools
Requires-Dist: argparse
Requires-Dist: playsound
